space/__init__.py
space/space.py
eloz_space-1.1.dist-info/METADATA
eloz_space-1.1.dist-info/WHEEL
eloz_space-1.1.dist-info/entry_points.txt
eloz_space-1.1.dist-info/top_level.txt
eloz_space-1.1.dist-info/RECORD
