Metadata-Version: 2.1
Name: eloz-space
Version: 1.1
Summary: A tool to display storage information
Home-page: https://github.com/yourusername/eloz-space
Author: eL0z
Author-email: your.email@example.com
Classifier: Programming Language :: Python :: 3
Classifier: License :: OSI Approved :: MIT License
Classifier: Operating System :: OS Independent
Requires-Python: >=3.6
Requires-Dist: psutil
